material_va_lighthouse/__init__.py
material_va_lighthouse/plugin.py
material_va_lighthouse/va_lighthouse.css
material_va_lighthouse/va_lighthouse_logo.png
material_va_lighthouse-1.2.1.dist-info/LICENSE
material_va_lighthouse-1.2.1.dist-info/METADATA
material_va_lighthouse-1.2.1.dist-info/WHEEL
material_va_lighthouse-1.2.1.dist-info/entry_points.txt
material_va_lighthouse-1.2.1.dist-info/top_level.txt
material_va_lighthouse-1.2.1.dist-info/RECORD
