Metadata-Version: 2.1
Name: material-va-lighthouse
Version: 1.2.1
Summary: A MKDocs plugin which extends the material theme with styles from the VA design system
Author: Alastair Dawson
Author-email: alastair.j.dawson@gmail.com
License: CC0 1.0
License-File: LICENSE
Requires-Dist: mkdocs (==1.4.3)
Requires-Dist: mkdocs-material (==8.1.11)
Requires-Dist: mkdocs-techdocs-core (==1.1.7)
